nonebot_plugin_matcher_block/__init__.py
nonebot_plugin_matcher_block/config.py
nonebot_plugin_matcher_block/core.py
nonebot_plugin_matcher_block-0.2.0.dist-info/LICENSE
nonebot_plugin_matcher_block-0.2.0.dist-info/METADATA
nonebot_plugin_matcher_block-0.2.0.dist-info/WHEEL
nonebot_plugin_matcher_block-0.2.0.dist-info/RECORD
