Metadata-Version: 2.1
Name: nonebot-plugin-matcher-block
Version: 0.2.0
Summary: 
Author: KarisAya
Author-email: 1048827424@qq.com
Requires-Python: >=3.12,<4.0
Classifier: Programming Language :: Python :: 3
Requires-Dist: nonebot-adapter-onebot (>=2.4.6,<3.0.0)
Requires-Dist: nonebot2 (>=2.4.0,<3.0.0)
Requires-Dist: pydantic (>=2.10.3,<3.0.0)
